cdk_cloudformation_newrelic_observability_ainotificationsdestination/__init__.py
cdk_cloudformation_newrelic_observability_ainotificationsdestination/py.typed
cdk_cloudformation_newrelic_observability_ainotificationsdestination/_jsii/__init__.py
cdk_cloudformation_newrelic_observability_ainotificationsdestination/_jsii/newrelic-observability-ainotificationsdestination@1.0.1-alpha.7.jsii.tgz
cdk_cloudformation_newrelic_observability_ainotificationsdestination-1.0.1a7.dist-info/LICENSE
cdk_cloudformation_newrelic_observability_ainotificationsdestination-1.0.1a7.dist-info/METADATA
cdk_cloudformation_newrelic_observability_ainotificationsdestination-1.0.1a7.dist-info/WHEEL
cdk_cloudformation_newrelic_observability_ainotificationsdestination-1.0.1a7.dist-info/top_level.txt
cdk_cloudformation_newrelic_observability_ainotificationsdestination-1.0.1a7.dist-info/RECORD
